aibash/__init__.py
aibash/ai_client.py
aibash/automation.py
aibash/config.py
aibash/config_init.py
aibash/context.py
aibash/history.py
aibash/i18n.py
aibash/interactive.py
aibash/main.py
aibash/prompt.py
aibash/summary_cache.py
aibash/agents/__init__.py
aibash/agents/agent_builder.py
aibash/agents/ollama_agent.py
aibash/agents/openai_agent.py
aibash/interfaces/__init__.py
aibash/interfaces/ai_agent.py
aibash/resources/__init__.py
aibash/utils/__init__.py
aibash/utils/clipboard.py
aibash/utils/keyboard.py
aibash/utils/terminal.py
aibash_wx-0.4.0.dist-info/licenses/LICENSE
aibash_wx-0.4.0.dist-info/METADATA
aibash_wx-0.4.0.dist-info/WHEEL
aibash_wx-0.4.0.dist-info/entry_points.txt
aibash_wx-0.4.0.dist-info/top_level.txt
aibash_wx-0.4.0.dist-info/RECORD
