Metadata-Version: 2.4
Name: aibash-wx
Version: 0.4.0
Summary: AI-powered shell command generator
Author: github/W1412X
License: MIT
Project-URL: Homepage, https://github.com/W1412X/aibash
Project-URL: Repository, https://github.com/W1412X/aibash
Keywords: ai,bash,shell,command,generator
Classifier: Development Status :: 3 - Alpha
Classifier: Intended Audience :: Developers
Classifier: Topic :: Utilities
Classifier: License :: OSI Approved :: MIT License
Classifier: Programming Language :: Python :: 3
Classifier: Programming Language :: Python :: 3.7
Classifier: Programming Language :: Python :: 3.8
Classifier: Programming Language :: Python :: 3.9
Classifier: Programming Language :: Python :: 3.10
Classifier: Programming Language :: Python :: 3.11
Classifier: Operating System :: OS Independent
Requires-Python: >=3.7
License-File: LICENSE
Requires-Dist: pyyaml>=5.4.1
Requires-Dist: requests>=2.25.1
Requires-Dist: urllib3>=1.26.0
Dynamic: license-file
